battdat/__init__.py
battdat/data.py
battdat/utils.py
battdat/version.py
battdat/consistency/__init__.py
battdat/consistency/base.py
battdat/consistency/current.py
battdat/io/__init__.py
battdat/io/arbin.py
battdat/io/ba.py
battdat/io/base.py
battdat/io/batterydata.py
battdat/io/hdf.py
battdat/io/maccor.py
battdat/io/parquet.py
battdat/postprocess/__init__.py
battdat/postprocess/base.py
battdat/postprocess/integral.py
battdat/postprocess/tagging.py
battdat/postprocess/timing.py
battdat/schemas/__init__.py
battdat/schemas/battery.py
battdat/schemas/column.py
battdat/schemas/cycling.py
battdat/schemas/eis.py
battdat/schemas/modeling.py
battdat/schemas/ontology.py
battdat/streaming/__init__.py
battdat/streaming/hdf5.py
battery_data_toolkit-0.4.6.dist-info/licenses/LICENSE
battery_data_toolkit-0.4.6.dist-info/METADATA
battery_data_toolkit-0.4.6.dist-info/WHEEL
battery_data_toolkit-0.4.6.dist-info/top_level.txt
battery_data_toolkit-0.4.6.dist-info/RECORD
