Metadata-Version: 2.4
Name: battery-data-toolkit
Version: 0.4.6
Summary: Utilities for reading and manipulating battery testing data
Author-email: Logan Ward <lward@anl.gov>, Noah Paulson <lward@anl.gov>, Joseph Kubal <kubal@anl.gov>
License:                                  Apache License
Project-URL: repository, https://github.com/rovi-org/battery-data-toolkit
Keywords: batteries,science,data science
Classifier: Development Status :: 4 - Beta
Classifier: Intended Audience :: Science/Research
Classifier: License :: OSI Approved :: Apache Software License
Classifier: Operating System :: OS Independent
Classifier: Topic :: File Formats
Classifier: Topic :: Scientific/Engineering
Requires-Python: >=3.10
License-File: LICENSE
Requires-Dist: pandas>1.0
Requires-Dist: scipy>1.3
Requires-Dist: pydantic==2.*
Requires-Dist: tables>3.6
Requires-Dist: pyarrow>=15
Requires-Dist: EMMOntoPy
Requires-Dist: xlrd
Provides-Extra: test
Requires-Dist: flake8; extra == "test"
Requires-Dist: pytest; extra == "test"
Requires-Dist: pytest-cov; extra == "test"
Provides-Extra: docs
Requires-Dist: sphinx; extra == "docs"
Requires-Dist: pydata-sphinx-theme; extra == "docs"
Requires-Dist: nbsphinx; extra == "docs"
Requires-Dist: autodoc-pydantic; extra == "docs"
Requires-Dist: sphinx-design; extra == "docs"
Dynamic: license-file
